COPYING
MANIFEST.in
README
health_inpatient_view.xml
setup.py
./__init__.py
./health_inpatient.py
./health_inpatient_view.xml
./tryton.cfg
./data/health_inpatient_sequence.xml
./data/inpatient_diets.xml
./doc/index.rst
./icons/cancel.svg
./icons/go-home.svg
./icons/hospital.svg
./icons/meals.svg
./icons/ok.svg
./locale/ar.po
./locale/de.po
./locale/el.po
./locale/es.po
./locale/fr.po
./locale/it_IT.po
./locale/ja_JP.po
./locale/lo.po
./locale/pt_BR.po
./locale/zh_CN.po
./security/access_rights.xml
./tests/__init__.py
./tests/test_health_inpatient.py
./view/ecg_registration.xml
./view/gnuhealth_bed_transfer_form.xml
./view/gnuhealth_bed_transfer_tree.xml
./view/gnuhealth_inpatient_diet_form.xml
./view/gnuhealth_inpatient_diet_therapeutic_form.xml
./view/gnuhealth_inpatient_diet_therapeutic_tree.xml
./view/gnuhealth_inpatient_diet_tree.xml
./view/gnuhealth_inpatient_meal_form.xml
./view/gnuhealth_inpatient_meal_order_form.xml
./view/gnuhealth_inpatient_meal_order_item_form.xml
./view/gnuhealth_inpatient_meal_order_item_tree.xml
./view/gnuhealth_inpatient_meal_order_tree.xml
./view/gnuhealth_inpatient_meal_tree.xml
./view/gnuhealth_inpatient_med_admin_time_form.xml
./view/gnuhealth_inpatient_med_admin_time_tree.xml
./view/gnuhealth_inpatient_med_log_form.xml
./view/gnuhealth_inpatient_med_log_tree.xml
./view/gnuhealth_inpatient_medication_form.xml
./view/gnuhealth_inpatient_medication_tree.xml
./view/gnuhealth_inpatient_registration.xml
./view/gnuhealth_inpatient_registration_tree.xml
./view/gnuhealth_patient_evaluation_form.xml
./view/gnuhealth_patient_extd_tree.xml
./view/partner_form.xml
./view/patient_bed_transfer.xml
./view/patient_form.xml
./wizard/__init__.py
./wizard/bed_transfer_wizard.xml
./wizard/inpatient_evaluation.xml
./wizard/wizard_health_inpatient.py
./wizard/wizard_inpatient_evaluation.py
data/health_inpatient_sequence.xml
data/inpatient_diets.xml
icons/README
icons/cancel.svg
icons/go-home.svg
icons/hospital.svg
icons/meals.svg
icons/ok.svg
trytond_health_inpatient.egg-info/PKG-INFO
trytond_health_inpatient.egg-info/SOURCES.txt
trytond_health_inpatient.egg-info/dependency_links.txt
trytond_health_inpatient.egg-info/entry_points.txt
trytond_health_inpatient.egg-info/not-zip-safe
trytond_health_inpatient.egg-info/requires.txt
trytond_health_inpatient.egg-info/top_level.txt
